<featureType>
  <id>FeatureTypeInfoImpl--5798cef1:147c5895640:-3325</id>
  <name>scotland_regions_simple</name>
  <nativeName>scotland_regions_simple</nativeName>
  <namespace>
    <id>NamespaceInfoImpl--19e1b629:13c90fa1a61:-7462</id>
  </namespace>
  <title>scotland_regions_simple</title>
  <keywords>
    <string>scotland_regions_simple</string>
    <string>features</string>
  </keywords>
  <srs>EPSG:4326</srs>
  <nativeBoundingBox>
    <minx>-8.65</minx>
    <maxx>-0.724444</maxx>
    <miny>54.6333</miny>
    <maxy>60.8607</maxy>
  </nativeBoundingBox>
  <latLonBoundingBox>
    <minx>-8.65</minx>
    <maxx>-0.724444</maxx>
    <miny>54.6333</miny>
    <maxy>60.8607</maxy>
    <crs>EPSG:4326</crs>
  </latLonBoundingBox>
  <projectionPolicy>FORCE_DECLARED</projectionPolicy>
  <enabled>true</enabled>
  <metadata>
    <entry key="cachingEnabled">false</entry>
  </metadata>
  <store class="dataStore">
    <id>DataStoreInfoImpl--5798cef1:147c5895640:-3326</id>
  </store>
  <serviceConfiguration>false</serviceConfiguration>
  <maxFeatures>0</maxFeatures>
  <numDecimals>0</numDecimals>
  <padWithZeros>false</padWithZeros>
  <forcedDecimal>false</forcedDecimal>
  <overridingServiceSRS>false</overridingServiceSRS>
  <skipNumberMatched>false</skipNumberMatched>
  <circularArcPresent>false</circularArcPresent>
</featureType>